weather_update/__init__.py
weather_update/weather.py
weather_update-1.0.1.dist-info/WHEEL
weather_update-1.0.1.dist-info/METADATA
weather_update-1.0.1.dist-info/RECORD
