Metadata-Version: 2.1
Name: weather-update
Version: 1.0.1
Summary: 
Author: Ashutosh Krishna
Author-email: ashutoshbritish@gmail.com
Requires-Python: >=3.9,<4.0
Classifier: Programming Language :: Python :: 3
Classifier: Programming Language :: Python :: 3.9
Classifier: Programming Language :: Python :: 3.10
Requires-Dist: requests (>=2.28.2,<3.0.0)
